pyds_sum/__init__.py
pyds_sum/summarize.py
pyds_sum-0.1.5.dist-info/LICENSE
pyds_sum-0.1.5.dist-info/METADATA
pyds_sum-0.1.5.dist-info/WHEEL
pyds_sum-0.1.5.dist-info/RECORD
